hyena/__init__.py
hyena/client.py
hyena/exceptions.py
hyena/nsfw_response.py
hyena/Async/__init__.py
hyena/Async/client.py
hyena/Sync/__init__.py
hyena/Sync/client.py
hyena_api.py-1.1.0.dist-info/LICENSE
hyena_api.py-1.1.0.dist-info/METADATA
hyena_api.py-1.1.0.dist-info/WHEEL
hyena_api.py-1.1.0.dist-info/top_level.txt
hyena_api.py-1.1.0.dist-info/RECORD
