Metadata-Version: 2.1
Name: hyena-api.py
Version: 1.1.0
Summary: A wrapper for the Hyena API.
Home-page: https://github.com/AHiddenDonut/hyena-api.py
Author: AHiddenDonut
Author-email: 31.siddhant.sharma@gmail.com
License: GNU General Public License v3.0
Keywords: wrapper,api-wrapper,hyena-api,python
Platform: UNKNOWN
Classifier: Development Status :: 1 - Planning
Classifier: Intended Audience :: Developers
Classifier: Programming Language :: Python :: 3
Classifier: Operating System :: Unix
Classifier: Topic :: Software Development :: Build Tools
Classifier: Operating System :: MacOS :: MacOS X
Classifier: Operating System :: Microsoft :: Windows
Requires-Python: >=3.6
Requires-Dist: requests
Requires-Dist: vcrpy
Requires-Dist: pytest
Requires-Dist: aiohttp
